numcodecs_shuffle/__init__.py
numcodecs_shuffle/py.typed
numcodecs_shuffle-0.1.0.dist-info/METADATA
numcodecs_shuffle-0.1.0.dist-info/WHEEL
numcodecs_shuffle-0.1.0.dist-info/entry_points.txt
numcodecs_shuffle-0.1.0.dist-info/licenses/LICENSE
numcodecs_shuffle-0.1.0.dist-info/RECORD
