Metadata-Version: 2.4
Name: numcodecs-shuffle
Version: 0.1.0
Summary: Typed byte shuffle codec for the `numcodecs` buffer compression API
License-Expression: MPL-2.0
License-File: LICENSE
Requires-Python: >=3.10
Requires-Dist: numcodecs<0.17,>=0.13.0
Requires-Dist: numpy~=2.0
